expression/__init__.py
expression/interpreter.py
expression/parser.py
expression_parser-0.0.6.dist-info/licenses/LICENSE
expression_parser-0.0.6.dist-info/METADATA
expression_parser-0.0.6.dist-info/WHEEL
expression_parser-0.0.6.dist-info/entry_points.txt
expression_parser-0.0.6.dist-info/top_level.txt
expression_parser-0.0.6.dist-info/RECORD
